gvc4bam/__init__.py
gvc4bam/bam_load_check.py
gvc4bam/bed_check_sort_reg.py
gvc4bam/check_runtime.py
gvc4bam/cnv.py
gvc4bam/gvc_check.py
gvc4bam/gvc_pipeline.py
gvc4bam/gvc_vcf_pipeline.py
gvc4bam/license_job.py
gvc4bam/predict.py
gvc4bam/qc_pipeline.py
gvc4bam/tb_bam_choice.py
gvc4bam/tb_split_ccd.py
gvc4bam/tb_test_check.py
gvc4bam/tb_volumes.py
gvc4bam/variant_interface.py
gvc4bam/vcf_oncodecode.py
gvc4bam-1.0.10.data/scripts/bam_vcf.py
gvc4bam-1.0.10.data/scripts/check_runtime.py
gvc4bam-1.0.10.dist-info/LICENSE
gvc4bam-1.0.10.dist-info/METADATA
gvc4bam-1.0.10.dist-info/WHEEL
gvc4bam-1.0.10.dist-info/top_level.txt
gvc4bam-1.0.10.dist-info/RECORD
